AlLoRa/DataSource.py
AlLoRa/Digital_Endpoint.py
AlLoRa/File.py
AlLoRa/Packet.py
AlLoRa/__init__.py
AlLoRa/Connectors/Connector.py
AlLoRa/Connectors/E5_connector.py
AlLoRa/Connectors/LoPy4_connector.py
AlLoRa/Connectors/SX1262_connector.py
AlLoRa/Connectors/SX127x_connector.py
AlLoRa/Connectors/Serial_connector.py
AlLoRa/Connectors/Wifi_connector.py
AlLoRa/Connectors/__init__.py
AlLoRa/Interfaces/Interface.py
AlLoRa/Interfaces/Serial_interface.py
AlLoRa/Interfaces/WiFi_interface.py
AlLoRa/Interfaces/__init__.py
AlLoRa/Nodes/Adapter.py
AlLoRa/Nodes/Gateway.py
AlLoRa/Nodes/Node.py
AlLoRa/Nodes/Requester.py
AlLoRa/Nodes/Source.py
AlLoRa/Nodes/__init__.py
AlLoRa/utils/__init__.py
AlLoRa/utils/debug_utils.py
AlLoRa/utils/json_utils.py
AlLoRa/utils/os_utils.py
AlLoRa/utils/time_utils.py
examples/__init__.py
examples/Adapters/__init__.py
examples/Adapters/Serial_adapter/__init__.py
examples/Adapters/Serial_adapter/main.py
examples/Adapters/WiFi_adapters/__init__.py
examples/Adapters/WiFi_adapters/WiFi-Client/__init__.py
examples/Adapters/WiFi_adapters/WiFi-Client/boot.py
examples/Adapters/WiFi_adapters/WiFi-Client/main_ESP32.py
examples/Adapters/WiFi_adapters/WiFi-Client/main_LoPy4.py
examples/Adapters/WiFi_adapters/WiFi-Hotspot/__init__.py
examples/Adapters/WiFi_adapters/WiFi-Hotspot/boot.py
examples/Adapters/WiFi_adapters/WiFi-Hotspot/main_ESP32.py
examples/Adapters/WiFi_adapters/WiFi-Hotspot/main_LoPy4.py
examples/Gateways/__init__.py
examples/Gateways/Serial_Gateway/__init__.py
examples/Gateways/Serial_Gateway/main.py
examples/Gateways/Serial_Gateway/rf_changer.py
examples/Gateways/Wifi_Gateway/__init__.py
examples/Gateways/Wifi_Gateway/main.py
examples/Requesters/__init__.py
examples/Requesters/LopyRequester/__init__.py
examples/Requesters/LopyRequester/boot.py
examples/Requesters/LopyRequester/main.py
examples/Requesters/T3S3/__init__.py
examples/Requesters/T3S3/main.py
examples/Requesters/T3S3/main_pro.py
examples/Sources/__init__.py
AlLoRa-2.0.0.dist-info/LICENSE
AlLoRa-2.0.0.dist-info/METADATA
AlLoRa-2.0.0.dist-info/WHEEL
AlLoRa-2.0.0.dist-info/top_level.txt
AlLoRa-2.0.0.dist-info/RECORD
