Metadata-Version: 2.2
Name: AlLoRa
Version: 2.0.0
Summary: Modular, mesh and multi-device Advanced LoRa Content Transfer Protocol for IoT applications
Author: Benjamín Arratia
Author-email: <hello@barratia.com>
Keywords: Python,Micropython,LoRa,mesh,IoT,Environmental Intelligence
Classifier: Development Status :: 5 - Production/Stable
Classifier: Intended Audience :: Developers
Classifier: License :: OSI Approved :: GNU General Public License v3 or later (GPLv3+)
Classifier: Programming Language :: Python :: 3
Classifier: Programming Language :: Python :: Implementation :: MicroPython
Classifier: Operating System :: Unix
Classifier: Operating System :: MacOS :: MacOS X
Classifier: Operating System :: Microsoft :: Windows
License-File: LICENSE
Dynamic: author
Dynamic: author-email
Dynamic: classifier
Dynamic: description
Dynamic: description-content-type
Dynamic: keywords
Dynamic: summary
